lokiunimore/config/__init__.py
lokiunimore/config/__main__.py
lokiunimore/config/config.py
lokiunimore/matrix/__init__.py
lokiunimore/matrix/__main__.py
lokiunimore/matrix/client.py
lokiunimore/matrix/templates/messages.py
lokiunimore/sql/__init__.py
lokiunimore/sql/__main__.py
lokiunimore/sql/tables.py
lokiunimore/utils/device_names.py
lokiunimore/utils/logs.py
lokiunimore/web/__init__.py
lokiunimore/web/__main__.py
lokiunimore/web/app.py
lokiunimore/web/extensions/matrix_client.py
lokiunimore/web/static/favicon.ico
lokiunimore/web/static/icon.png
lokiunimore/web/static/newcode.png
lokiunimore/web/static/opengraph.png
lokiunimore/web/static/rooms.png
lokiunimore/web/static/s-192.png
lokiunimore/web/static/spaces.png
lokiunimore/web/static/thor.png
lokiunimore/web/static/unimore.css
lokiunimore/web/static/verify.png
lokiunimore/web/templates/_base.html
lokiunimore/web/templates/errors/_base.html
lokiunimore/web/templates/errors/failed-invite.html
lokiunimore/web/templates/errors/no-link.html
lokiunimore/web/templates/errors/not-found.html
lokiunimore/web/templates/errors/not-student.html
lokiunimore/web/templates/errors/not-verified.html
lokiunimore/web/templates/errors/oidc.html
lokiunimore/web/templates/errors/rate-invite.html
lokiunimore/web/templates/matrix/complete.html
lokiunimore/web/templates/matrix/join.html
lokiunimore/web/templates/matrix/verify.html
lokiunimore/web/templates/privacy.html
lokiunimore/web/templates/root.html
lokiunimore-0.7.1.dist-info/WHEEL
lokiunimore-0.7.1.dist-info/LICENSE.txt
lokiunimore-0.7.1.dist-info/entry_points.txt
lokiunimore-0.7.1.dist-info/METADATA
lokiunimore-0.7.1.dist-info/RECORD
