Metadata-Version: 2.1
Name: lokiunimore
Version: 0.7.1
Summary: Matrix room gatekeeper bot for the unofficial Unimore space
Home-page: https://loki.steffo.eu/
License: AGPL-3.0-or-later
Keywords: bot,matrix,authentication,unimore,oauth2
Author: Stefano Pigozzi
Author-email: me@steffo.eu
Maintainer: Stefano Pigozzi
Maintainer-email: me@steffo.eu
Requires-Python: >=3.10,<4.0
Classifier: License :: OSI Approved :: GNU Affero General Public License v3 or later (AGPLv3+)
Classifier: Programming Language :: Python :: 3
Classifier: Programming Language :: Python :: 3.10
Classifier: Programming Language :: Python :: 3.11
Classifier: Programming Language :: Python :: 3
Classifier: Programming Language :: Python :: 3.10
Requires-Dist: Authlib (>=1.0.1,<2.0.0)
Requires-Dist: Flask (>=2.2.2,<3.0.0)
Requires-Dist: Flask-SQLAlchemy (>=3.0.0,<4.0.0)
Requires-Dist: cfig[cli] (>=0.3.0,<0.4.0)
Requires-Dist: coloredlogs (>=15.0.1,<16.0.0)
Requires-Dist: gunicorn (>=20.1.0,<21.0.0)
Requires-Dist: matrix-nio (>=0.20.1,<0.21.0)
Requires-Dist: psycopg2 (>=2.9.3,<3.0.0)
Requires-Dist: python-dotenv (>=1.0.0,<2.0.0)
Requires-Dist: requests (>=2.28.1,<3.0.0)
Project-URL: Repository, https://github.com/Steffo99/lokiunimore
